{
  "_class": "symbolInstance",
  "booleanOperation": -1,
  "do_objectID": "CF77FBC9-406F-4129-8C88-67DED910948F",
  "exportOptions": {
    "_class": "exportOptions",
    "exportFormats": [
    ],
    "includedLayerIds": [
    ],
    "layerOptions": 0,
    "shouldTrim": false
  },
  "frame": {
    "_class": "rect",
    "constrainProportions": false,
    "height": 34,
    "width": 170,
    "x": 708,
    "y": 262
  },
  "horizontalSpacing": 0,
  "isFixedToViewport": false,
  "isFlippedHorizontal": false,
  "isFlippedVertical": false,
  "isLocked": false,
  "isVisible": true,
  "layerListExpandedType": 0,
  "name": "Buttons/Regular Copy 14",
  "nameIsFixed": true,
  "overrideValues": [
    {
      "_class": "overrideValue",
      "do_objectID": "2D8EA7EB-477F-450A-8529-ED1F33762E77",
      "overrideName": "FBD90DDD-1324-4A77-BE02-CB74D777CE2D_symbolID",
      "value": "DA0E6A93-9CB1-4710-80F5-4497E3ECC0D9"
    },
    {
      "_class": "overrideValue",
      "do_objectID": "741187C5-45FB-481C-8D5F-42EF9B4A52C8",
      "overrideName": "223026C9-B2CE-46DC-B076-0535C8ECAD99_stringValue",
      "value": "Add Account"
    }
  ],
  "resizingConstraint": 63,
  "resizingType": 0,
  "rotation": 0,
  "scale": 1,
  "shouldBreakMaskChain": false,
  "style": {
    "_class": "style",
    "endMarkerType": 0,
    "miterLimit": 10,
    "startMarkerType": 0,
    "windingRule": 1
  },
  "symbolID": "C9FC3A61-55F7-469E-8D4C-45BCE1C9FF5E",
  "userInfo": {
    "com.animaapp.stc-sketch-plugin": {
      "kModelPropertiesKey": {
      }
    }
  },
  "verticalSpacing": 0
}